[
  {
    "title": "[Cardician] Курс карточных фокусов и кардистри «0,5+0,5»",
    "url": "https://cloud.mail.ru/public/dPrX/X5BUoNEt9",
    "cloud": "Облако"
  },
  {
    "title": "[Фокусы] Алекс Дарен ― Token (2024)",
    "url": "https://cloud.mail.ru/public/dADr/JyJVPeUYC",
    "cloud": "Облако"
  },
  {
    "title": "[Александр Шишук, Евгений Горланов] Jazz Magic (2023)",
    "url": "https://cloud.mail.ru/public/99Ue/WHBcE2U6B",
    "cloud": "Облако"
  },
  {
    "title": "Видеоуроки по фокусам для детей и родителей",
    "url": "https://cloud.mail.ru/public/mh6n/TXdH4xnvR",
    "cloud": "Облако"
  },
  {
    "title": "[ФигАсебе] Мануэль Ясэр, Денис Чертовский - Ментализм 2: Материальность мысли (2014)",
    "url": "https://cloud.mail.ru/public/wgrX/9G3yDuCAG",
    "cloud": "Облако"
  },
  {
    "title": "[ФигАсебе] Ментализм",
    "url": "https://cloud.mail.ru/public/29B8/3k25ekG9b",
    "cloud": "Облако"
  },
  {
    "title": "[Гол Ди Айэн] Призрачный уголок (2017)",
    "url": "https://cloud.mail.ru/public/4yd7/3d8Qbnagf",
    "cloud": "Облако"
  },
  {
    "title": "Alex - Фокус Paper Shed (2019)",
    "url": "https://cloud.mail.ru/public/Qkk8/ZMomc323W",
    "cloud": "Облако"
  },
  {
    "title": "[Сергей Полевов] Книга по ментализму \"Лимурия\" (2017)",
    "url": "https://cloud.mail.ru/public/fEfR/zvL3o9nBv",
    "cloud": "Облако"
  },
  {
    "title": "[Наталья Никулина] [Relax Gamak] Дуэт (2024)",
    "url": "https://cloud.mail.ru/public/icB3/upc9bbenV",
    "cloud": "Облако"
  },
  {
    "title": "[Лилия Завадская] Сборник Зефирные подарки (2022)",
    "url": "https://cloud.mail.ru/public/WWhs/zYyTtetaE",
    "cloud": "Облако"
  },
  {
    "title": "[Дмитрий Сорокин] Онлайн-курс английского языка. Тариф Интенсив (2025)",
    "url": "https://cloud.mail.ru/public/kkkS/qEqa4C12y",
    "cloud": "Облако"
  },
  {
    "title": "[Наташа Фелицына] [Felitsyna school] Макияж для себя. Продвинутый (2024)",
    "url": "https://cloud.mail.ru/public/9DTR/igNkPMd1z",
    "cloud": "Облако"
  },
  {
    "title": "[Антон Назаров] Подписка на контент Осознанная меркантильность. Тариф Vip волк. Май (2025)",
    "url": "https://cloud.mail.ru/public/n3oV/wRB2DRSyj",
    "cloud": "Облако"
  },
  {
    "title": "[Антон Назаров] Подписка на контент Осознанная меркантильность. Тариф Vip волк. Июнь (2025)",
    "url": "https://cloud.mail.ru/public/Kb1N/imeAb91cG",
    "cloud": "Облако"
  },
  {
    "title": "[Антон Назаров] Подписка на контент Осознанная меркантильность. Тариф Волчара (Июль 2025)",
    "url": "https://cloud.mail.ru/public/xFf3/qaPtaxm9n",
    "cloud": "Облако"
  },
  {
    "title": "[Антон Назаров] Подписка на контент Осознанная меркантильность. Тариф Волчара (Август 2025)",
    "url": "https://cloud.mail.ru/public/vjZW/3Qt5MEiLx",
    "cloud": "Облако"
  },
  {
    "title": "[Антон Назаров] Подписка на контент Осознанная меркантильность. Тариф Волчара (Сентябрь 2025)",
    "url": "https://cloud.mail.ru/public/fYpS/e55iupj6r",
    "cloud": "Облако"
  },
  {
    "title": "[Антон Назаров] Подписка на контент Осознанная меркантильность. Тариф Волчара (Октябрь 2025)",
    "url": "https://cloud.mail.ru/public/ApB3/CAd1nxdfh",
    "cloud": "Облако"
  },
  {
    "title": "[Captain Swan] Сумка в стиле Birkin",
    "url": "https://cloud.mail.ru/public/aj6v/oFFFJcGiu",
    "cloud": "Облако"
  },
  {
    "title": "[Андрей Богатырев] [rehab science] Протокол реабилитации колена с упражнениями",
    "url": "https://disk.yandex.ru/d/tfaW6QrrU8z5Ww",
    "cloud": "Облако"
  },
  {
    "title": "[Дмитрий Зверев] Конструктор промптов. Тариф Конструктор промптов (2025)",
    "url": "https://cloud.mail.ru/public/BH88/iTq46pdve",
    "cloud": "Облако"
  },
  {
    "title": "[slurm] Golang-разработчик (2023)",
    "url": "https://cloud.mail.ru/public/g6iJ/q1Lo1Qq7o",
    "cloud": "Облако"
  },
  {
    "title": "[Игорь Новокриницкий] Малышовый фитнес для детей 3-6 месяцев (2023)",
    "url": "https://cloud.mail.ru/public/ThUL/cLkBk6D4o",
    "cloud": "Облако"
  },
  {
    "title": "[Игорь Новокриницкий] Малышовый фитнес для детей 6-9 месяцев (2023)",
    "url": "https://cloud.mail.ru/public/SPFb/Aes82EXcA",
    "cloud": "Облако"
  },
  {
    "title": "[Игорь Новокриницкий] Малышовый фитнес для детей 9-12 месяцев (2023)",
    "url": "https://cloud.mail.ru/public/3thk/Qd3rb9VRW",
    "cloud": "Облако"
  },
  {
    "title": "[Оксана Авдеева, Школа нейрографики] Pro деньги 2.0. Тариф Максимальный (2023)",
    "url": "https://cloud.mail.ru/public/X9Cg/yxtwrBJbg",
    "cloud": "Облако"
  },
  {
    "title": "[Марк Николаев] Курс по нейросетям (2025)",
    "url": "https://cloud.mail.ru/public/XVAv/jX45W9tgQ",
    "cloud": "Облако"
  },
  {
    "title": "[Olga Larnaudie] [Lalavanda.school] Косметика для лица. PRO (2025)",
    "url": "https://cloud.mail.ru/public/1MhY/kmn41KWcr",
    "cloud": "Облако"
  },
  {
    "title": "[Маргулан Сейсембаев] Миссия. Икигай (2021)",
    "url": "https://cloud.mail.ru/public/ukp4/i1b5FMZZd",
    "cloud": "Облако"
  },
  {
    "title": "[Виктория Ракуса] [Vikisews] Марафон по пошиву пальто Маред (2023)",
    "url": "https://cloud.mail.ru/public/LW92/EKQLSXN1E",
    "cloud": "Облако"
  },
  {
    "title": "[Олег Макаренко, Кримсональтер] Клуб Зеленой Свиньи. Тариф Клубная карточка (07.10-05.11.2025)",
    "url": "https://cloud.mail.ru/public/61c5/c3ezJzPQ2",
    "cloud": "Облако"
  },
  {
    "title": "[Алексей Шадрин] Сумрачный германский гений — Оскар Кокошка (2025)",
    "url": "https://cloud.mail.ru/public/JkaD/LCjyXptgK",
    "cloud": "Облако"
  },
  {
    "title": "[Константин Михайлов] [Таким путем] Китай. От древних династий до современности. Лекция 4. Эпоха Тан (2025)",
    "url": "https://cloud.mail.ru/public/HGt5/dnU9yAEBK",
    "cloud": "Облако"
  },
  {
    "title": "[Сергей Лопатин] [Архэ] Лимбическая система и вокруг неё: нейробиология эмоций и чувств. Лекция 6. Нейробиология любви (2025)",
    "url": "https://cloud.mail.ru/public/ZVEx/ndKJ3o9iS",
    "cloud": "Облако"
  },
  {
    "title": "[Константин Михайлов] Эпоха Возрождения. Лекция 3. Князья и тираны (2025)",
    "url": "https://cloud.mail.ru/public/om7j/3EsMGXfZM",
    "cloud": "Облако"
  },
  {
    "title": "[Сергей Лопатин] Лимбическая система и вокруг неё: нейробиология эмоций и чувств. Лекция 4. Не гормон счастья. Зачем нам серотонин? (2025)",
    "url": "https://cloud.mail.ru/public/pvab/enqq7xkhu",
    "cloud": "Облако"
  },
  {
    "title": "[Кримсон Альтер, Виктор Мараховский] Средство немассовой информации СНМИ (Октябрь 2025)",
    "url": "https://cloud.mail.ru/public/ujko/6VZ2eEDCS",
    "cloud": "Облако"
  },
  {
    "title": "[Константин Михайлов] Религиозный детектив. Сезон 7. Лекция 6. Империя хиппи (2025)",
    "url": "https://cloud.mail.ru/public/9kVS/HLsSoUEyK",
    "cloud": "Облако"
  },
  {
    "title": "[Сергей Лопатин] Лимбическая система и вокруг неё: нейробиология эмоций и чувств. Лекция 5 (2025)",
    "url": "https://cloud.mail.ru/public/MkWm/VRFL3g848",
    "cloud": "Облако"
  },
  {
    "title": "[Виктор Мараховский] Подписка на тексты Виктора Мараховского (Октябрь 2025)",
    "url": "https://cloud.mail.ru/public/W3Aj/pEHL4cRD2",
    "cloud": "Облако"
  },
  {
    "title": "[Валерий Соловей] Революция сверху (2025)",
    "url": "https://cloud.mail.ru/public/pUZ5/wL68oBpZX",
    "cloud": "Облако"
  },
  {
    "title": "[Константин Михайлов] Религиозный детектив. Сезон 7. Лекция 8. Мрачный финал (2025)",
    "url": "https://cloud.mail.ru/public/Ysjk/ZGMomqMEG",
    "cloud": "Облако"
  },
  {
    "title": "[Александр Шумский] 3 в 1: светофоры, перекрестки и новые ПДД (2025)",
    "url": "https://cloud.mail.ru/public/6rxC/snAdWnn7x",
    "cloud": "Облако"
  },
  {
    "title": "[Дмитрий Скворцов, Алёна Ванченко] [Синхронизация] Гид по фильмам ужасов (2025)",
    "url": "https://cloud.mail.ru/public/QHgP/oXaMgnwKD",
    "cloud": "Облако"
  },
  {
    "title": "[Точка интеллекта] Иван Негреев ― Колдовство и магия в истории религий. Южная Азия: Индия и Иран. Лекция 5. Джйотиш: ведическая астрология (2025)",
    "url": "https://cloud.mail.ru/public/sDyu/b9oqSV7AA",
    "cloud": "Облако"
  },
  {
    "title": "[Точка интеллекта] Иван Негреев ― Китайская философия. Лекция 5. Система перемен в китайской философии и Книга перемен. Часть 3 (2025)",
    "url": "https://cloud.mail.ru/public/ooUF/gCE11yJB2",
    "cloud": "Облако"
  },
  {
    "title": "[Зеленая стрела] Елена Смирнова ― Выращивание овощей в теплице на садовом участке (2020)",
    "url": "https://cloud.mail.ru/public/GBmQ/aCPCdN2kr",
    "cloud": "Облако"
  },
  {
    "title": "[Садовый Гид] Лариса Зарубина ― Огурцы. Инструкция по выращиванию (2022)",
    "url": "https://cloud.mail.ru/public/6Aue/G8nHFbNvk",
    "cloud": "Облако"
  },
  {
    "title": "[Константин Михайлов] [Таким путем] Китай. От древних династий до современности. Лекция 3. Великая эпоха распада (2025)",
    "url": "https://cloud.mail.ru/public/crQE/WhWCE5Wxy",
    "cloud": "Облако"
  },
  {
    "title": "[Александр Панчин] Думай как ученый в эпоху инфошума. Тариф Базовый (2025)",
    "url": "https://cloud.mail.ru/public/Zdid/28L3U9Z8D",
    "cloud": "Облако"
  },
  {
    "title": "[Архэ] Антон Захаров ― Что физиологи знают про еду? Полезная и вредная еда, как следить за рационом. Лекция 3 (2025)",
    "url": "https://cloud.mail.ru/public/1FEj/fKSczwnyb",
    "cloud": "Облако"
  },
  {
    "title": "[Точка интеллекта] Иван Негреев ― Китайская философия: от конфуцианства до даосизма. Лекция 4. Книга Перемен. Часть 2 (2025)",
    "url": "https://cloud.mail.ru/public/hhgp/aKGyk6ifR",
    "cloud": "Облако"
  },
  {
    "title": "[Точка интеллекта] Иван Негреев ― Колдовство и магия в истории религий. Южная Азия: Индия и Иран. Лекция 4. Магия в индуизме. Часть 2 (2025)",
    "url": "https://cloud.mail.ru/public/G8C9/GvxP9rG2x",
    "cloud": "Облако"
  },
  {
    "title": "[Academy Chisto Blisto] Левон Тонян ― Оборудование и инструменты (2025)",
    "url": "https://cloud.mail.ru/public/C8Uw/Bzey46PTG",
    "cloud": "Облако"
  },
  {
    "title": "[Сергей Лопатин] [Архэ] Лимбическая система и вокруг неё: нейробиология эмоций и чувств. Базальные ядра: нейробиология привычек. Лекция 3 (2025)",
    "url": "https://cloud.mail.ru/public/FZWc/V2jQEzwKN",
    "cloud": "Облако"
  },
  {
    "title": "[Точка интеллекта] Иван Негреев ― Китайская философия: от конфуцианства до даосизма. Лекция 3 (2025)",
    "url": "https://cloud.mail.ru/public/3Yxo/tPFgJV4v5",
    "cloud": "Облако"
  },
  {
    "title": "[Сергей Лопатин] [Архэ] Лимбическая система и вокруг неё: нейробиология мотиваций. На что способен дофамин на самом деле? Лекция 2 (2025)",
    "url": "https://cloud.mail.ru/public/uHFd/HBLNGYn5j",
    "cloud": "Облако"
  },
  {
    "title": "[Сергей Лопатин] [Архэ] Лимбическая система и вокруг неё: нейробиология эмоций и чувств. Радость познания. Нейробиология любопытства. Лекция 1 (2025)",
    "url": "https://cloud.mail.ru/public/tuda/DNcBX5UzE",
    "cloud": "Облако"
  },
  {
    "title": "[Точка интеллекта] Иван Негреев ― Китайская философия: от конфуцианства до даосизма. Лекция 2 (2025)",
    "url": "https://cloud.mail.ru/public/Hm8k/bBTphnSAP",
    "cloud": "Облако"
  },
  {
    "title": "[Точка интеллекта] Иван Негреев ― Китайская философия: от конфуцианства до даосизма. Лекция 1 (2025)",
    "url": "https://cloud.mail.ru/public/DBxr/ZdaRDeVSP",
    "cloud": "Облако"
  },
  {
    "title": "[АстроГарден] Любовь Забуслаева ― Видеокурс по уходу за садом «Профессиональные секреты» (2025)",
    "url": "https://cloud.mail.ru/public/E5gP/ohDhVTSog",
    "cloud": "Облако"
  },
  {
    "title": "[Точка интеллекта] Иван Негреев ― Колдовство и магия в истории религий. Южная Азия: Индия и Иран. Лекция 3 (2025)",
    "url": "https://cloud.mail.ru/public/A8bL/xH5w9WGxK",
    "cloud": "Облако"
  },
  {
    "title": "[Антон Кислицын] АвтоТренер (2025)",
    "url": "https://cloud.mail.ru/public/wYch/wd8ofmE9m",
    "cloud": "Облако"
  },
  {
    "title": "[Наталья Виноградова] Полный порядок 3.0. Тариф Lite (2025)",
    "url": "https://cloud.mail.ru/public/LK3J/jNzDisYEv",
    "cloud": "Облако"
  },
  {
    "title": "[Точка интеллекта] Иван Негреев ― Колдовство и магия в истории религий. Южная Азия: Индия и Иран. Лекция 2 (2025)",
    "url": "https://cloud.mail.ru/public/BNGJ/8xXaecqtg",
    "cloud": "Облако"
  },
  {
    "title": "[anfi] Наталья Спиридонова ― Дрессировка с любовью (2024)",
    "url": "https://cloud.mail.ru/public/tRt3/Hzqefrnwk",
    "cloud": "Облако"
  },
  {
    "title": "[TutorPlace] Мария Выговская ― Дрессировка собак (2025)",
    "url": "https://cloud.mail.ru/public/ErRe/tGLCb9yVJ",
    "cloud": "Облако"
  },
  {
    "title": "[Таким путем] Константин Михайлов ― Китай. От древних династий до современности. Лекция 2. Первые китайские империи (2025)",
    "url": "https://cloud.mail.ru/public/iCAY/mBQKZmTmg",
    "cloud": "Облако"
  },
  {
    "title": "[Константин Михайлов] Религиозный детектив. Сезон 7. Лекция 7. Политическое убийство (2025)",
    "url": "https://cloud.mail.ru/public/bbpR/QkNSdsHBo",
    "cloud": "Облако"
  },
  {
    "title": "[plants.coach] Яна Строинская ― Лагерь с цветочками 4.0. Тариф Основной (2025)",
    "url": "https://cloud.mail.ru/public/qpP3/JX9cg9u3D",
    "cloud": "Облако"
  },
  {
    "title": "[Иван Негреев] [Точка интеллекта] Философский читательский клуб Ивана Негреева: Платон (2025)",
    "url": "https://cloud.mail.ru/public/sxi7/UQ2vAUv8h",
    "cloud": "Облако"
  },
  {
    "title": "[Наталья Невская] [Институт Адвокатуры] Общая юрисдикция под ключ (2025)",
    "url": "https://cloud.mail.ru/public/hNt5/FNTKbypXk",
    "cloud": "Облако"
  },
  {
    "title": "[Любовь Попова] Борис Кустодиев (2025)",
    "url": "https://cloud.mail.ru/public/5i38/3qpD4Ergk",
    "cloud": "Облако"
  },
  {
    "title": "[Олег Макаренко, Кримсональтер] Клуб Зеленой Свиньи. Тариф Клубная карточка (05.09-05.10.2025)",
    "url": "https://cloud.mail.ru/public/vvc1/sSqhf5fuX",
    "cloud": "Облако"
  },
  {
    "title": "[Константин Михайлов] Эпоха Возрождения. Лекция 2. Города и республики (2025)",
    "url": "https://cloud.mail.ru/public/5syg/ZAw4CAp4J",
    "cloud": "Облако"
  },
  {
    "title": "[Педагоги России] Сборник педагогических промптов. 2000 запросов для нейросетей, которые перевернут ваш мир (2025)",
    "url": "https://cloud.mail.ru/public/6tx1/ebZQn9qho",
    "cloud": "Облако"
  },
  {
    "title": "[Ярмарка сценариев] Стас Щеглов ― Караоке игра «Меломан» (2025)",
    "url": "https://cloud.mail.ru/public/JWxX/TxUMdbgzV",
    "cloud": "Облако"
  },
  {
    "title": "[Точка интеллекта] Иван Негреев ― Колдовство и магия в истории религий. Южная Азия: Индия и Иран. Лекция 1. Магические гимны Вед (2025)",
    "url": "https://cloud.mail.ru/public/qAz8/yVvaiqpUA",
    "cloud": "Облако"
  },
  {
    "title": "[Страдариум] Александра Архипова ― Происхождение любви 18+ (2025)",
    "url": "https://cloud.mail.ru/public/QR8i/irujEmna1",
    "cloud": "Облако"
  },
  {
    "title": "[Наталья Виноградова] 250 органайзеров для порядка в детской комнате (2025)",
    "url": "https://cloud.mail.ru/public/XxdM/r34e3McS5",
    "cloud": "Облако"
  },
  {
    "title": "[Тарас Дударь] Основы профессиональной чистки мягкой мебели (2025)",
    "url": "https://cloud.mail.ru/public/DFP4/7JMLaxV1j",
    "cloud": "Облако"
  },
  {
    "title": "[Виктор Мараховский] Подписка на тексты Виктора Мараховского. Сентябрь (2025)",
    "url": "https://cloud.mail.ru/public/fYgq/MK4NFeMPs",
    "cloud": "Облако"
  },
  {
    "title": "[Level One] Гульнара Гайфуллина ― Генеалогия: учимся искать и составлять историю своей семьи (2023)",
    "url": "https://cloud.mail.ru/public/6yhE/Je9iHhzXG",
    "cloud": "Облако"
  },
  {
    "title": "[Дарья Босомыкина] [Архэ] «История дизайна. Как вещи меняли мир». Лекция 2. Германия и Австрия. Баухауз и мечта о новом человеке, дизайн Третьего рейха и Ульмская школа (2025)",
    "url": "https://cloud.mail.ru/public/AxZq/YAKYkR9rx",
    "cloud": "Облако"
  }
]
